watson/__init__.py
watson/di/__init__.py
watson/di/container.py
watson/di/exceptions.py
watson/di/processors.py
watson/di/types.py
watson_di-2.2.4.dist-info/AUTHORS
watson_di-2.2.4.dist-info/LICENSE
watson_di-2.2.4.dist-info/METADATA
watson_di-2.2.4.dist-info/WHEEL
watson_di-2.2.4.dist-info/top_level.txt
watson_di-2.2.4.dist-info/RECORD
