Metadata-Version: 2.1
Name: watson-di
Version: 2.2.4
Summary: Dependency Injection made simple.
Home-page: http://github.com/watsonpy/watson-di
Author: Simon Coulton
Author-email: simon@bespohk.com
License: Copyright (c) Bespohk and individual contributors.
Requires-Dist: watson-common (>=1.1.0)
Requires-Dist: watson-events (>=1.0.2)
Provides-Extra: test
Requires-Dist: pytest ; extra == 'test'
Requires-Dist: pytest-cov ; extra == 'test'
Requires-Dist: coverage ; extra == 'test'
Requires-Dist: coveralls ; extra == 'test'
